gmx_ffconv/__init__.py
gmx_ffconv/cli.py
gmx_ffconv/utilities/__init__.py
gmx_ffconv/utilities/ffmap.py
gmx_ffconv/utilities/groconv.py
gmx_ffconv/utilities/utilities_ffmap/__init__.py
gmx_ffconv/utilities/utilities_ffmap/file_reader.py
gmx_ffconv/utilities/utilities_ffmap/graph_functions.py
gmx_ffconv/utilities/utilities_ffmap/mapping_naming.py
gmx_ffconv/utilities/utilities_ffmap/mapping_standard.py
gmx_ffconv/utilities/utilities_groconv/__init__.py
gmx_ffconv/utilities/utilities_groconv/coordinate_reorganise.py
gmx_ffconv/utilities/utilities_groconv/functions_for_groconv.py
gmx_ffconv/utilities/utilities_plotting/__init__.py
gmx_ffconv-1.0.3.post1.dist-info/licenses/LICENSE
gmx_ffconv-1.0.3.post1.dist-info/METADATA
gmx_ffconv-1.0.3.post1.dist-info/WHEEL
gmx_ffconv-1.0.3.post1.dist-info/entry_points.txt
gmx_ffconv-1.0.3.post1.dist-info/top_level.txt
gmx_ffconv-1.0.3.post1.dist-info/RECORD
