Metadata-Version: 2.4
Name: gmx_ffconv
Version: 1.0.3.post1
Summary: An automated GROMACS force field converter tool
Author: Jasmine E. Aaltonen
License:                                  Apache License
Project-URL: Homepage, https://github.com/Jassu1998/gmx_ffconv
Project-URL: Bug Tracker, https://github.com/Jassu1998/gmx_ffconv/issues
Requires-Python: >=3.8
License-File: LICENSE
Requires-Dist: numpy
Requires-Dist: networkx
Dynamic: license-file
